<?xml version="1.0" encoding="UTF-8"?><vmap:VMAP xmlns:vmap="http://www.iab.net/videosuite/vmap" version="1.0"><vmap:AdBreak breakType="linear" timeOffset="start"><vmap:AdSource><vmap:VASTAdData>

<VAST xmlns:xsi="http://www.w3.org/2001/XMLSchema-instance" xsi:noNamespaceSchemaLocation="vast.xsd" version="2.0">
  <Ad id="5640305240501">
    <InLine>
      <AdSystem>Amazon</AdSystem>
      <AdTitle><![CDATA[854x480_Pre-roll_2020 Consumer Card OLV Proposal_15_WFBR_VEN_CVEN_JG_ Demo_Creative 2_1650146-2]]></AdTitle>
      <Error><![CDATA[https://s.amazon-adsystem.com/iui3?d=forester-did&ex-fargs=%3Fi%3DE3cwbesMob4zFiPJ-uqMhw%26e%3DvideoError%26a%3D5640305240501%26c%3D6822625010601%26s%3Dpda%26u%3DE3cwbesMob4zFiPJ-uqMhw&ex-fch=416719&cb=8,134,718,304,092,249,943]]></Error>
      <Impression><![CDATA[https://aax-us-east.amazon-adsystem.com/v/imp?b=IhN3MG3rDKG-MxYjyfrqjIcAAAFwRTCtxAEAAADMBGfIC7g&bi=piW9TS205.U2pWWplyeA19s0ziNrdW6K6TUj.8aTPQFP5j1BlY0uHf9T7UD3iYy.BmZD-WXcq-agq1e4rbE.7pE3C-gjG5e9nQdLCYyONuvOKlSJ8QQ6EsN8xUt4z.FSKxGhP0vZMSCMhBng-5fIW-rS8V-p0TkGH97kT6.uzb663oI9i.tii7-Uude7C.mYgd2GjiEEd5ICpTQgOyNlpCSRnVcfESt31GF.jPj7ivolFfavSAuFliLxzFH8JR61gMKrcz6tgs35VX7k3.8tVnFVtYXVmDIVGoW8plfbX47QncH-alMK-fbqgJb1qRNTvcFK0.gFRmxwFn2TtYN18WJwiIBURKj9u8OV-w4y6zd47gO0q2WUjaJ3CfvYlQsfjQTqP4DScJecSfdpUaH63akQ7fwmb-ZMy6gqhxZ.nmtjcHXzfyiR14iR1A.v7xlCCoJLeT474bOO2NXMTMuwYniUgBF.ILKbNU8y6HlWl2-rgcxKFi1HC5C1okj3f-OQ]]></Impression><Impression><![CDATA[https://s.amazon-adsystem.com/iui3?d=forester-did&ex-fargs=%3Fi%3DE3cwbesMob4zFiPJ-uqMhw%26e%3DvideoImpression%26a%3D5640305240501%26c%3D6822625010601%26s%3Dpda%26u%3DE3cwbesMob4zFiPJ-uqMhw&ex-fch=416719&cb=6,009,703,333,239,374,515]]></Impression>
       <Impression><![CDATA[https://dts.innovid.com/placement/1i4lff/video/1jt3qp/action/play/cb/5,340,929,669,894,881,999]]></Impression> <Impression><![CDATA[https://secure.insightexpressai.com/adServer/adServerESI.aspx?script=false&bannerID=6223042&siteID=949&creativeID=521795&placementID=1650146&rnd=1,613,151,346,328,946,071&redir=https://secure.insightexpressai.com/adserver/1pixel.gif]]></Impression> <Impression><![CDATA[https://tps30.doubleverify.com/visit.jpg?ctx=1069526&cmp=90841&sid=949&plc=1650146&crt=521795&adsrv=118&dvtagver=6.1.img&tagtype=video]]></Impression> <Impression><![CDATA[https://d.agkn.com/pixel/7267/?che=&col=90841,949,1650146,0,521795]]></Impression> <Impression><![CDATA[https://secure-gl.imrworldwide.com/cgi-bin/m?ca=nlsn203231&cr=521795&ce=949&pc=1650146&ci=nlsnci39&am=52&at=view&rt=banner&st=image&r=7,081,692,223,943,172,290]]></Impression>
      <Creatives>
          <Creative sequence="1" id="6822625010601">
              <Linear>
              <Duration>00:00:15</Duration>
                  <TrackingEvents>
   <Tracking event="start"><![CDATA[https://s.amazon-adsystem.com/iui3?d=forester-did&ex-fargs=%3Fi%3DE3cwbesMob4zFiPJ-uqMhw%26e%3DvideoStart%26a%3D5640305240501%26c%3D6822625010601%26s%3Dpda%26u%3DE3cwbesMob4zFiPJ-uqMhw&ex-fch=416719&cb=5,267,008,634,980,303,090]]></Tracking>
   <Tracking event="firstQuartile"><![CDATA[https://s.amazon-adsystem.com/iui3?d=forester-did&ex-fargs=%3Fi%3DE3cwbesMob4zFiPJ-uqMhw%26e%3DvideoFirstQuartile%26a%3D5640305240501%26c%3D6822625010601%26s%3Dpda%26u%3DE3cwbesMob4zFiPJ-uqMhw&ex-fch=416719&cb=3,302,162,476,188,817,526]]></Tracking>
   <Tracking event="midpoint"><![CDATA[https://s.amazon-adsystem.com/iui3?d=forester-did&ex-fargs=%3Fi%3DE3cwbesMob4zFiPJ-uqMhw%26e%3DvideoMidpoint%26a%3D5640305240501%26c%3D6822625010601%26s%3Dpda%26u%3DE3cwbesMob4zFiPJ-uqMhw&ex-fch=416719&cb=5,224,223,841,982,079,458]]></Tracking>
   <Tracking event="thirdQuartile"><![CDATA[https://s.amazon-adsystem.com/iui3?d=forester-did&ex-fargs=%3Fi%3DE3cwbesMob4zFiPJ-uqMhw%26e%3DvideoThirdQuartile%26a%3D5640305240501%26c%3D6822625010601%26s%3Dpda%26u%3DE3cwbesMob4zFiPJ-uqMhw&ex-fch=416719&cb=1,271,076,680,719,283,655]]></Tracking>
   <Tracking event="complete"><![CDATA[https://s.amazon-adsystem.com/iui3?d=forester-did&ex-fargs=%3Fi%3DE3cwbesMob4zFiPJ-uqMhw%26e%3DvideoComplete%26a%3D5640305240501%26c%3D6822625010601%26s%3Dpda%26u%3DE3cwbesMob4zFiPJ-uqMhw&ex-fch=416719&cb=3,334,280,663,543,207,890]]></Tracking>
   <Tracking event="mute"><![CDATA[https://s.amazon-adsystem.com/iui3?d=forester-did&ex-fargs=%3Fi%3DE3cwbesMob4zFiPJ-uqMhw%26e%3DvideoMute%26a%3D5640305240501%26c%3D6822625010601%26s%3Dpda%26u%3DE3cwbesMob4zFiPJ-uqMhw&ex-fch=416719&cb=1,307,005,600,100,285,855]]></Tracking>
   <Tracking event="unmute"><![CDATA[https://s.amazon-adsystem.com/iui3?d=forester-did&ex-fargs=%3Fi%3DE3cwbesMob4zFiPJ-uqMhw%26e%3DvideoUnmute%26a%3D5640305240501%26c%3D6822625010601%26s%3Dpda%26u%3DE3cwbesMob4zFiPJ-uqMhw&ex-fch=416719&cb=890,094,368,517,862,396]]></Tracking>
   <Tracking event="pause"><![CDATA[https://s.amazon-adsystem.com/iui3?d=forester-did&ex-fargs=%3Fi%3DE3cwbesMob4zFiPJ-uqMhw%26e%3DvideoPause%26a%3D5640305240501%26c%3D6822625010601%26s%3Dpda%26u%3DE3cwbesMob4zFiPJ-uqMhw&ex-fch=416719&cb=2,477,996,900,925,772,796]]></Tracking>
   <Tracking event="resume"><![CDATA[https://s.amazon-adsystem.com/iui3?d=forester-did&ex-fargs=%3Fi%3DE3cwbesMob4zFiPJ-uqMhw%26e%3DvideoResume%26a%3D5640305240501%26c%3D6822625010601%26s%3Dpda%26u%3DE3cwbesMob4zFiPJ-uqMhw&ex-fch=416719&cb=2,902,825,495,390,324,770]]></Tracking>
   <Tracking event="rewind"><![CDATA[https://s.amazon-adsystem.com/iui3?d=forester-did&ex-fargs=%3Fi%3DE3cwbesMob4zFiPJ-uqMhw%26e%3DvideoSkipBackward%26a%3D5640305240501%26c%3D6822625010601%26s%3Dpda%26u%3DE3cwbesMob4zFiPJ-uqMhw&ex-fch=416719&cb=465,718,439,532,590,128]]></Tracking>
   <Tracking event="acceptInvitation"><![CDATA[https://s.amazon-adsystem.com/iui3?d=forester-did&ex-fargs=%3Fi%3DE3cwbesMob4zFiPJ-uqMhw%26e%3DvideoCreativeView%26a%3D5640305240501%26c%3D6822625010601%26s%3Dpda%26u%3DE3cwbesMob4zFiPJ-uqMhw&ex-fch=416719&cb=1,418,907,347,043,352,657]]></Tracking>
   <Tracking event="close"><![CDATA[https://s.amazon-adsystem.com/iui3?d=forester-did&ex-fargs=%3Fi%3DE3cwbesMob4zFiPJ-uqMhw%26e%3DvideoClose%26a%3D5640305240501%26c%3D6822625010601%26s%3Dpda%26u%3DE3cwbesMob4zFiPJ-uqMhw&ex-fch=416719&cb=9,022,460,348,387,588,172]]></Tracking>
<Tracking event="start"><![CDATA[https://aax-us-east.amazon-adsystem.com/x/px/IhN3MG3rDKG-MxYjyfrqjIcAAAFwRTCtxAEAAADMBGfIC7g/%7B%22c%22%3A%22video%22%2C%22src%22%3A204%2C%22start%22%3A1%7D]]></Tracking><Tracking event="firstQuartile"><![CDATA[https://aax-us-east.amazon-adsystem.com/x/px/IhN3MG3rDKG-MxYjyfrqjIcAAAFwRTCtxAEAAADMBGfIC7g/%7B%221q%22%3A1%2C%22c%22%3A%22video%22%2C%22src%22%3A204%7D]]></Tracking><Tracking event="midpoint"><![CDATA[https://aax-us-east.amazon-adsystem.com/x/px/IhN3MG3rDKG-MxYjyfrqjIcAAAFwRTCtxAEAAADMBGfIC7g/%7B%22c%22%3A%22video%22%2C%22src%22%3A204%2C%222q%22%3A1%7D]]></Tracking><Tracking event="thirdQuartile"><![CDATA[https://aax-us-east.amazon-adsystem.com/x/px/IhN3MG3rDKG-MxYjyfrqjIcAAAFwRTCtxAEAAADMBGfIC7g/%7B%22c%22%3A%22video%22%2C%22src%22%3A204%2C%223q%22%3A1%7D]]></Tracking><Tracking event="complete"><![CDATA[https://aax-us-east.amazon-adsystem.com/x/px/IhN3MG3rDKG-MxYjyfrqjIcAAAFwRTCtxAEAAADMBGfIC7g/%7B%22c%22%3A%22video%22%2C%22src%22%3A204%2C%22cpl%22%3A1%7D]]></Tracking><Tracking event="pause"><![CDATA[https://aax-us-east.amazon-adsystem.com/x/px/IhN3MG3rDKG-MxYjyfrqjIcAAAFwRTCtxAEAAADMBGfIC7g/%7B%22p%22%3A1%2C%22c%22%3A%22video%22%2C%22src%22%3A204%7D]]></Tracking><Tracking event="resume"><![CDATA[https://aax-us-east.amazon-adsystem.com/x/px/IhN3MG3rDKG-MxYjyfrqjIcAAAFwRTCtxAEAAADMBGfIC7g/%7B%22r%22%3A1%2C%22c%22%3A%22video%22%2C%22src%22%3A204%7D]]></Tracking></TrackingEvents>
                  <VideoClicks>
                    <ClickThrough><![CDATA[https://aax-us-east.amazon-adsystem.com/x/c/QhN3MG3rDKG-MxYjyfrqjIcAAAFwRTCtsQEAAADMBGfIC7g/https://dts.innovid.com/placement/1i4lff/video/1jt3qp/action/clktru/cb/2,094,616,914,917,757,231]]></ClickThrough>
                    <ClickTracking><![CDATA[https://s.amazon-adsystem.com/iui3?d=forester-did&ex-fargs=%3Fi%3DE3cwbesMob4zFiPJ-uqMhw%26e%3DvideoClick%26a%3D5640305240501%26c%3D6822625010601%26s%3Dpda%26u%3DE3cwbesMob4zFiPJ-uqMhw&ex-fch=416719&cb=7,584,352,748,945,508,515]]></ClickTracking>
                  <ClickTracking><![CDATA[https://aax-us-east.amazon-adsystem.com/x/px/IhN3MG3rDKG-MxYjyfrqjIcAAAFwRTCtxAEAAADMBGfIC7g/%7B%22c%22%3A%22video%22%2C%22clk%22%3A1%2C%22src%22%3A204%7D]]></ClickTracking></VideoClicks>
                  <MediaFiles>
                    <MediaFile height="1080" width="1920" bitrate="1340" type="application/x-shockwave-flash" delivery="progressive" apiFramework="VPAID">
                      <![CDATA[https://images-na.ssl-images-amazon.com/images/G/01/d16g/kpw/vpaid-2.swf]]>
                    </MediaFile>
                    <MediaFile height="0" width="0" delivery="progressive" type="application/javascript" apiFramework="VPAID">
                        <![CDATA[https://images-na.ssl-images-amazon.com/images/G/01/d16g/kpw/v/vpaid-013d10c31f7bd9a6c26d.bundle.min.js]]>
                    </MediaFile>
                      <MediaFile height="1080" width="1920" bitrate="1340" type="application/x-shockwave-flash" delivery="progressive" apiFramework="VPAID">
                        <![CDATA[https://images-na.ssl-images-amazon.com/images/G/01/d16g/kpw/vpaid-1.swf]]>
                      </MediaFile>
                  </MediaFiles>
                  <AdParameters><![CDATA[<videoUrl>https://cdn-a.amazon-adsystem.com/video/159a0e49-3038-4b75-85a8-95495923ac55/1350-1920x1080.flv</videoUrl>
                      <clickUrl>https://aax-us-east.amazon-adsystem.com/x/c/QhN3MG3rDKG-MxYjyfrqjIcAAAFwRTCtsQEAAADMBGfIC7g/https://dts.innovid.com/placement/1i4lff/video/1jt3qp/action/clktru/cb/2,094,616,914,917,757,231</clickUrl>
                      <adDuration>15</adDuration>
                      <adPrefUrl>https://www.amazon.com/adprefs</adPrefUrl>
                      <showAdNotice>0</showAdNotice>
                      <expandableAdChoices>1</expandableAdChoices>
                      <JsParameters>
                        {"duration":15,"clickThruUrl":"https://aax-us-east.amazon-adsystem.com/x/c/QhN3MG3rDKG-MxYjyfrqjIcAAAFwRTCtsQEAAADMBGfIC7g/https://dts.innovid.com/placement/1i4lff/video/1jt3qp/action/clktru/cb/2,094,616,914,917,757,231","showAdChoices":false,"skippableState":false,"adChoicesLocale":"US","vuInstr":"https://aax-us-east.amazon-adsystem.com/x/px/IhN3MG3rDKG-MxYjyfrqjIcAAAFwRTCtxAEAAADMBGfIC7g/","adCfid":5640305240501,"creativeCfid":6822625010601,"videos":[{"mimetype":"video/mp4","url":"https://cdn-a.amazon-adsystem.com/video/159a0e49-3038-4b75-85a8-95495923ac55/10000-1920x1080.mp4"},{"mimetype":"video/mp4","url":"https://cdn-a.amazon-adsystem.com/video/159a0e49-3038-4b75-85a8-95495923ac55/3000-1920x1080.mp4"},{"mimetype":"video/mp4","url":"https://cdn-a.amazon-adsystem.com/video/159a0e49-3038-4b75-85a8-95495923ac55/2000-1920x1080.mp4"},{"mimetype":"video/webm","url":"https://cdn-a.amazon-adsystem.com/video/159a0e49-3038-4b75-85a8-95495923ac55/1350-1920x1080.webm"},{"mimetype":"video/mp4","url":"https://cdn-a.amazon-adsystem.com/video/159a0e49-3038-4b75-85a8-95495923ac55/1350-1920x1080.mp4"},{"mimetype":"video/x-flv","url":"https://cdn-a.amazon-adsystem.com/video/159a0e49-3038-4b75-85a8-95495923ac55/1350-1920x1080.flv"},{"mimetype":"video/mp4","url":"https://cdn-a.amazon-adsystem.com/video/159a0e49-3038-4b75-85a8-95495923ac55/900-1920x1080.mp4"},{"mimetype":"video/mp4","url":"https://cdn-a.amazon-adsystem.com/video/159a0e49-3038-4b75-85a8-95495923ac55/600-1920x1080.mp4"},{"mimetype":"video/mp4","url":"https://cdn-a.amazon-adsystem.com/video/159a0e49-3038-4b75-85a8-95495923ac55/450-1920x1080.mp4"},{"mimetype":"video/mp4","url":"https://cdn-a.amazon-adsystem.com/video/159a0e49-3038-4b75-85a8-95495923ac55/300-1920x1080.mp4"}],"vpaidVersion":"2.0","vu":"//imdb.amazon-adsystem.com/imdb-csm/webvideo/csm.js"}
                      </JsParameters>]]></AdParameters>
              </Linear>
          </Creative>
      </Creatives>
    </InLine>
  </Ad>
</VAST><!-- creativeModDate = 1580323167000 -->

</vmap:VASTAdData></vmap:AdSource></vmap:AdBreak></vmap:VMAP>
